{"validation_loss": 0.4899073839187622, "validation_mean": 0.4609440863132477, "time_this_iter_s": 2900.4656801223755, "done": false, "timesteps_total": null, "episodes_total": null, "training_iteration": 1, "trial_id": "d56098f2", "experiment_id": "e0994ea7d18644288cf38cad106100d7", "date": "2022-06-13_23-43-43", "timestamp": 1655135023, "time_total_s": 2900.4656801223755, "pid": 68460, "hostname": "localhost.localdomain", "node_ip": "192.168.249.74", "config": {"batch_size": 14, "beta1": 0.9, "beta2": 0.999, "lr": 0.0012134882085154237, "weight_decay": 1.3602984953647424e-05, "__trial_index__": 0}, "time_since_restore": 2900.4656801223755, "timesteps_since_restore": 0, "iterations_since_restore": 1}
{"validation_loss": 0.5379364490509033, "validation_mean": 0.3627113401889801, "time_this_iter_s": 2841.006798028946, "done": false, "timesteps_total": null, "episodes_total": null, "training_iteration": 2, "trial_id": "d56098f2", "experiment_id": "e0994ea7d18644288cf38cad106100d7", "date": "2022-06-14_00-31-04", "timestamp": 1655137864, "time_total_s": 5741.472478151321, "pid": 68460, "hostname": "localhost.localdomain", "node_ip": "192.168.249.74", "config": {"batch_size": 14, "beta1": 0.9, "beta2": 0.999, "lr": 0.0012134882085154237, "weight_decay": 1.3602984953647424e-05, "__trial_index__": 0}, "time_since_restore": 5741.472478151321, "timesteps_since_restore": 0, "iterations_since_restore": 2}
{"validation_loss": 0.43849119544029236, "validation_mean": 0.5848825573921204, "time_this_iter_s": 2871.4392392635345, "done": false, "timesteps_total": null, "episodes_total": null, "training_iteration": 3, "trial_id": "d56098f2", "experiment_id": "e0994ea7d18644288cf38cad106100d7", "date": "2022-06-14_01-18-55", "timestamp": 1655140735, "time_total_s": 8612.911717414856, "pid": 68460, "hostname": "localhost.localdomain", "node_ip": "192.168.249.74", "config": {"batch_size": 14, "beta1": 0.9, "beta2": 0.999, "lr": 0.0012134882085154237, "weight_decay": 1.3602984953647424e-05, "__trial_index__": 0}, "time_since_restore": 8612.911717414856, "timesteps_since_restore": 0, "iterations_since_restore": 3}
{"validation_loss": 0.3932618498802185, "validation_mean": 0.7005584836006165, "time_this_iter_s": 2855.9337220191956, "done": false, "timesteps_total": null, "episodes_total": null, "training_iteration": 4, "trial_id": "d56098f2", "experiment_id": "e0994ea7d18644288cf38cad106100d7", "date": "2022-06-14_02-06-31", "timestamp": 1655143591, "time_total_s": 11468.845439434052, "pid": 68460, "hostname": "localhost.localdomain", "node_ip": "192.168.249.74", "config": {"batch_size": 14, "beta1": 0.9, "beta2": 0.999, "lr": 0.0012134882085154237, "weight_decay": 1.3602984953647424e-05, "__trial_index__": 0}, "time_since_restore": 11468.845439434052, "timesteps_since_restore": 0, "iterations_since_restore": 4}
{"validation_loss": 0.5125899314880371, "validation_mean": 0.429117888212204, "time_this_iter_s": 2814.52942442894, "done": false, "timesteps_total": null, "episodes_total": null, "training_iteration": 5, "trial_id": "d56098f2", "experiment_id": "e0994ea7d18644288cf38cad106100d7", "date": "2022-06-14_02-53-26", "timestamp": 1655146406, "time_total_s": 14283.374863862991, "pid": 68460, "hostname": "localhost.localdomain", "node_ip": "192.168.249.74", "config": {"batch_size": 14, "beta1": 0.9, "beta2": 0.999, "lr": 0.0012134882085154237, "weight_decay": 1.3602984953647424e-05, "__trial_index__": 0}, "time_since_restore": 14283.374863862991, "timesteps_since_restore": 0, "iterations_since_restore": 5}
{"validation_loss": 0.3721012771129608, "validation_mean": 0.7500573992729187, "time_this_iter_s": 2815.57545876503, "done": false, "timesteps_total": null, "episodes_total": null, "training_iteration": 6, "trial_id": "d56098f2", "experiment_id": "e0994ea7d18644288cf38cad106100d7", "date": "2022-06-14_03-40-21", "timestamp": 1655149221, "time_total_s": 17098.95032262802, "pid": 68460, "hostname": "localhost.localdomain", "node_ip": "192.168.249.74", "config": {"batch_size": 14, "beta1": 0.9, "beta2": 0.999, "lr": 0.0012134882085154237, "weight_decay": 1.3602984953647424e-05, "__trial_index__": 0}, "time_since_restore": 17098.95032262802, "timesteps_since_restore": 0, "iterations_since_restore": 6}
{"validation_loss": 0.4929904639720917, "validation_mean": 0.47203734517097473, "time_this_iter_s": 2816.211733818054, "done": false, "timesteps_total": null, "episodes_total": null, "training_iteration": 7, "trial_id": "d56098f2", "experiment_id": "e0994ea7d18644288cf38cad106100d7", "date": "2022-06-14_04-27-18", "timestamp": 1655152038, "time_total_s": 19915.162056446075, "pid": 68460, "hostname": "localhost.localdomain", "node_ip": "192.168.249.74", "config": {"batch_size": 14, "beta1": 0.9, "beta2": 0.999, "lr": 0.0012134882085154237, "weight_decay": 1.3602984953647424e-05, "__trial_index__": 0}, "time_since_restore": 19915.162056446075, "timesteps_since_restore": 0, "iterations_since_restore": 7}
{"validation_loss": 0.4816689193248749, "validation_mean": 0.5043990612030029, "time_this_iter_s": 2855.436203956604, "done": false, "timesteps_total": null, "episodes_total": null, "training_iteration": 8, "trial_id": "d56098f2", "experiment_id": "e0994ea7d18644288cf38cad106100d7", "date": "2022-06-14_05-14-53", "timestamp": 1655154893, "time_total_s": 22770.59826040268, "pid": 68460, "hostname": "localhost.localdomain", "node_ip": "192.168.249.74", "config": {"batch_size": 14, "beta1": 0.9, "beta2": 0.999, "lr": 0.0012134882085154237, "weight_decay": 1.3602984953647424e-05, "__trial_index__": 0}, "time_since_restore": 22770.59826040268, "timesteps_since_restore": 0, "iterations_since_restore": 8}
{"validation_loss": 0.45813703536987305, "validation_mean": 0.5566521286964417, "time_this_iter_s": 2866.7128672599792, "done": false, "timesteps_total": null, "episodes_total": null, "training_iteration": 9, "trial_id": "d56098f2", "experiment_id": "e0994ea7d18644288cf38cad106100d7", "date": "2022-06-14_06-02-40", "timestamp": 1655157760, "time_total_s": 25637.31112766266, "pid": 68460, "hostname": "localhost.localdomain", "node_ip": "192.168.249.74", "config": {"batch_size": 14, "beta1": 0.9, "beta2": 0.999, "lr": 0.0012134882085154237, "weight_decay": 1.3602984953647424e-05, "__trial_index__": 0}, "time_since_restore": 25637.31112766266, "timesteps_since_restore": 0, "iterations_since_restore": 9}
{"validation_loss": 0.48434990644454956, "validation_mean": 0.495218425989151, "time_this_iter_s": 2869.6874480247498, "done": false, "timesteps_total": null, "episodes_total": null, "training_iteration": 10, "trial_id": "d56098f2", "experiment_id": "e0994ea7d18644288cf38cad106100d7", "date": "2022-06-14_06-50-29", "timestamp": 1655160629, "time_total_s": 28506.99857568741, "pid": 68460, "hostname": "localhost.localdomain", "node_ip": "192.168.249.74", "config": {"batch_size": 14, "beta1": 0.9, "beta2": 0.999, "lr": 0.0012134882085154237, "weight_decay": 1.3602984953647424e-05, "__trial_index__": 0}, "time_since_restore": 28506.99857568741, "timesteps_since_restore": 0, "iterations_since_restore": 10}
{"validation_loss": 0.44044384360313416, "validation_mean": 0.5971999168395996, "time_this_iter_s": 2870.853899002075, "done": false, "timesteps_total": null, "episodes_total": null, "training_iteration": 11, "trial_id": "d56098f2", "experiment_id": "e0994ea7d18644288cf38cad106100d7", "date": "2022-06-14_07-38-20", "timestamp": 1655163500, "time_total_s": 31377.852474689484, "pid": 68460, "hostname": "localhost.localdomain", "node_ip": "192.168.249.74", "config": {"batch_size": 14, "beta1": 0.9, "beta2": 0.999, "lr": 0.0012134882085154237, "weight_decay": 1.3602984953647424e-05, "__trial_index__": 0}, "time_since_restore": 31377.852474689484, "timesteps_since_restore": 0, "iterations_since_restore": 11}
{"validation_loss": 0.5063634514808655, "validation_mean": 0.4429653286933899, "time_this_iter_s": 2888.9652614593506, "done": false, "timesteps_total": null, "episodes_total": null, "training_iteration": 12, "trial_id": "d56098f2", "experiment_id": "e0994ea7d18644288cf38cad106100d7", "date": "2022-06-14_08-26-29", "timestamp": 1655166389, "time_total_s": 34266.817736148834, "pid": 68460, "hostname": "localhost.localdomain", "node_ip": "192.168.249.74", "config": {"batch_size": 14, "beta1": 0.9, "beta2": 0.999, "lr": 0.0012134882085154237, "weight_decay": 1.3602984953647424e-05, "__trial_index__": 0}, "time_since_restore": 34266.817736148834, "timesteps_since_restore": 0, "iterations_since_restore": 12}
{"validation_loss": 0.4525706470012665, "validation_mean": 0.47999387979507446, "time_this_iter_s": 2867.9429216384888, "done": false, "timesteps_total": null, "episodes_total": null, "training_iteration": 13, "trial_id": "d56098f2", "experiment_id": "e0994ea7d18644288cf38cad106100d7", "date": "2022-06-14_09-14-17", "timestamp": 1655169257, "time_total_s": 37134.76065778732, "pid": 68460, "hostname": "localhost.localdomain", "node_ip": "192.168.249.74", "config": {"batch_size": 14, "beta1": 0.9, "beta2": 0.999, "lr": 0.0012134882085154237, "weight_decay": 1.3602984953647424e-05, "__trial_index__": 0}, "time_since_restore": 37134.76065778732, "timesteps_since_restore": 0, "iterations_since_restore": 13}
{"validation_loss": 0.49721845984458923, "validation_mean": 0.4635452628135681, "time_this_iter_s": 2874.0428564548492, "done": false, "timesteps_total": null, "episodes_total": null, "training_iteration": 14, "trial_id": "d56098f2", "experiment_id": "e0994ea7d18644288cf38cad106100d7", "date": "2022-06-14_10-02-11", "timestamp": 1655172131, "time_total_s": 40008.80351424217, "pid": 68460, "hostname": "localhost.localdomain", "node_ip": "192.168.249.74", "config": {"batch_size": 14, "beta1": 0.9, "beta2": 0.999, "lr": 0.0012134882085154237, "weight_decay": 1.3602984953647424e-05, "__trial_index__": 0}, "time_since_restore": 40008.80351424217, "timesteps_since_restore": 0, "iterations_since_restore": 14}
{"validation_loss": 0.5106913447380066, "validation_mean": 0.4335551857948303, "time_this_iter_s": 2868.819216489792, "done": false, "timesteps_total": null, "episodes_total": null, "training_iteration": 15, "trial_id": "d56098f2", "experiment_id": "e0994ea7d18644288cf38cad106100d7", "date": "2022-06-14_10-50-00", "timestamp": 1655175000, "time_total_s": 42877.622730731964, "pid": 68460, "hostname": "localhost.localdomain", "node_ip": "192.168.249.74", "config": {"batch_size": 14, "beta1": 0.9, "beta2": 0.999, "lr": 0.0012134882085154237, "weight_decay": 1.3602984953647424e-05, "__trial_index__": 0}, "time_since_restore": 42877.622730731964, "timesteps_since_restore": 0, "iterations_since_restore": 15}
{"validation_loss": 0.4665273129940033, "validation_mean": 0.531481921672821, "time_this_iter_s": 2842.8398184776306, "done": false, "timesteps_total": null, "episodes_total": null, "training_iteration": 16, "trial_id": "d56098f2", "experiment_id": "e0994ea7d18644288cf38cad106100d7", "date": "2022-06-14_11-37-23", "timestamp": 1655177843, "time_total_s": 45720.462549209595, "pid": 68460, "hostname": "localhost.localdomain", "node_ip": "192.168.249.74", "config": {"batch_size": 14, "beta1": 0.9, "beta2": 0.999, "lr": 0.0012134882085154237, "weight_decay": 1.3602984953647424e-05, "__trial_index__": 0}, "time_since_restore": 45720.462549209595, "timesteps_since_restore": 0, "iterations_since_restore": 16}
{"validation_loss": 0.5287867784500122, "validation_mean": 0.39545559883117676, "time_this_iter_s": 2869.530693292618, "done": false, "timesteps_total": null, "episodes_total": null, "training_iteration": 17, "trial_id": "d56098f2", "experiment_id": "e0994ea7d18644288cf38cad106100d7", "date": "2022-06-14_12-25-12", "timestamp": 1655180712, "time_total_s": 48589.99324250221, "pid": 68460, "hostname": "localhost.localdomain", "node_ip": "192.168.249.74", "config": {"batch_size": 14, "beta1": 0.9, "beta2": 0.999, "lr": 0.0012134882085154237, "weight_decay": 1.3602984953647424e-05, "__trial_index__": 0}, "time_since_restore": 48589.99324250221, "timesteps_since_restore": 0, "iterations_since_restore": 17}
{"validation_loss": 0.39201274514198303, "validation_mean": 0.7066789269447327, "time_this_iter_s": 2852.0759694576263, "done": false, "timesteps_total": null, "episodes_total": null, "training_iteration": 18, "trial_id": "d56098f2", "experiment_id": "e0994ea7d18644288cf38cad106100d7", "date": "2022-06-14_13-12-44", "timestamp": 1655183564, "time_total_s": 51442.06921195984, "pid": 68460, "hostname": "localhost.localdomain", "node_ip": "192.168.249.74", "config": {"batch_size": 14, "beta1": 0.9, "beta2": 0.999, "lr": 0.0012134882085154237, "weight_decay": 1.3602984953647424e-05, "__trial_index__": 0}, "time_since_restore": 51442.06921195984, "timesteps_since_restore": 0, "iterations_since_restore": 18}
{"validation_loss": 0.5074903964996338, "validation_mean": 0.4418177604675293, "time_this_iter_s": 2823.521199941635, "done": false, "timesteps_total": null, "episodes_total": null, "training_iteration": 19, "trial_id": "d56098f2", "experiment_id": "e0994ea7d18644288cf38cad106100d7", "date": "2022-06-14_13-59-48", "timestamp": 1655186388, "time_total_s": 54265.590411901474, "pid": 68460, "hostname": "localhost.localdomain", "node_ip": "192.168.249.74", "config": {"batch_size": 14, "beta1": 0.9, "beta2": 0.999, "lr": 0.0012134882085154237, "weight_decay": 1.3602984953647424e-05, "__trial_index__": 0}, "time_since_restore": 54265.590411901474, "timesteps_since_restore": 0, "iterations_since_restore": 19}
{"validation_loss": 0.5003132820129395, "validation_mean": 0.45780736207962036, "time_this_iter_s": 2850.851930618286, "done": false, "timesteps_total": null, "episodes_total": null, "training_iteration": 20, "trial_id": "d56098f2", "experiment_id": "e0994ea7d18644288cf38cad106100d7", "date": "2022-06-14_14-47-19", "timestamp": 1655189239, "time_total_s": 57116.44234251976, "pid": 68460, "hostname": "localhost.localdomain", "node_ip": "192.168.249.74", "config": {"batch_size": 14, "beta1": 0.9, "beta2": 0.999, "lr": 0.0012134882085154237, "weight_decay": 1.3602984953647424e-05, "__trial_index__": 0}, "time_since_restore": 57116.44234251976, "timesteps_since_restore": 0, "iterations_since_restore": 20}
{"validation_loss": 0.47945263981819153, "validation_mean": 0.5042460560798645, "time_this_iter_s": 2878.663318157196, "done": false, "timesteps_total": null, "episodes_total": null, "training_iteration": 21, "trial_id": "d56098f2", "experiment_id": "e0994ea7d18644288cf38cad106100d7", "date": "2022-06-14_15-35-17", "timestamp": 1655192117, "time_total_s": 59995.105660676956, "pid": 68460, "hostname": "localhost.localdomain", "node_ip": "192.168.249.74", "config": {"batch_size": 14, "beta1": 0.9, "beta2": 0.999, "lr": 0.0012134882085154237, "weight_decay": 1.3602984953647424e-05, "__trial_index__": 0}, "time_since_restore": 59995.105660676956, "timesteps_since_restore": 0, "iterations_since_restore": 21}
{"validation_loss": 0.5542225241661072, "validation_mean": 0.3350929617881775, "time_this_iter_s": 2842.016435146332, "done": false, "timesteps_total": null, "episodes_total": null, "training_iteration": 22, "trial_id": "d56098f2", "experiment_id": "e0994ea7d18644288cf38cad106100d7", "date": "2022-06-14_16-22-39", "timestamp": 1655194959, "time_total_s": 62837.12209582329, "pid": 68460, "hostname": "localhost.localdomain", "node_ip": "192.168.249.74", "config": {"batch_size": 14, "beta1": 0.9, "beta2": 0.999, "lr": 0.0012134882085154237, "weight_decay": 1.3602984953647424e-05, "__trial_index__": 0}, "time_since_restore": 62837.12209582329, "timesteps_since_restore": 0, "iterations_since_restore": 22}
{"validation_loss": 0.4554623067378998, "validation_mean": 0.5433402061462402, "time_this_iter_s": 2867.2140548229218, "done": false, "timesteps_total": null, "episodes_total": null, "training_iteration": 23, "trial_id": "d56098f2", "experiment_id": "e0994ea7d18644288cf38cad106100d7", "date": "2022-06-14_17-10-27", "timestamp": 1655197827, "time_total_s": 65704.33615064621, "pid": 68460, "hostname": "localhost.localdomain", "node_ip": "192.168.249.74", "config": {"batch_size": 14, "beta1": 0.9, "beta2": 0.999, "lr": 0.0012134882085154237, "weight_decay": 1.3602984953647424e-05, "__trial_index__": 0}, "time_since_restore": 65704.33615064621, "timesteps_since_restore": 0, "iterations_since_restore": 23}
{"validation_loss": 0.45357993245124817, "validation_mean": 0.5691224932670593, "time_this_iter_s": 2850.3500056266785, "done": false, "timesteps_total": null, "episodes_total": null, "training_iteration": 24, "trial_id": "d56098f2", "experiment_id": "e0994ea7d18644288cf38cad106100d7", "date": "2022-06-14_17-57-57", "timestamp": 1655200677, "time_total_s": 68554.68615627289, "pid": 68460, "hostname": "localhost.localdomain", "node_ip": "192.168.249.74", "config": {"batch_size": 14, "beta1": 0.9, "beta2": 0.999, "lr": 0.0012134882085154237, "weight_decay": 1.3602984953647424e-05, "__trial_index__": 0}, "time_since_restore": 68554.68615627289, "timesteps_since_restore": 0, "iterations_since_restore": 24}
{"validation_loss": 0.46324580907821655, "validation_mean": 0.5460944175720215, "time_this_iter_s": 2840.2436785697937, "done": false, "timesteps_total": null, "episodes_total": null, "training_iteration": 25, "trial_id": "d56098f2", "experiment_id": "e0994ea7d18644288cf38cad106100d7", "date": "2022-06-14_18-45-17", "timestamp": 1655203517, "time_total_s": 71394.92983484268, "pid": 68460, "hostname": "localhost.localdomain", "node_ip": "192.168.249.74", "config": {"batch_size": 14, "beta1": 0.9, "beta2": 0.999, "lr": 0.0012134882085154237, "weight_decay": 1.3602984953647424e-05, "__trial_index__": 0}, "time_since_restore": 71394.92983484268, "timesteps_since_restore": 0, "iterations_since_restore": 25}
{"validation_loss": 0.3838837742805481, "validation_mean": 0.7303190231323242, "time_this_iter_s": 2832.7485222816467, "done": false, "timesteps_total": null, "episodes_total": null, "training_iteration": 26, "trial_id": "d56098f2", "experiment_id": "e0994ea7d18644288cf38cad106100d7", "date": "2022-06-14_19-32-30", "timestamp": 1655206350, "time_total_s": 74227.67835712433, "pid": 68460, "hostname": "localhost.localdomain", "node_ip": "192.168.249.74", "config": {"batch_size": 14, "beta1": 0.9, "beta2": 0.999, "lr": 0.0012134882085154237, "weight_decay": 1.3602984953647424e-05, "__trial_index__": 0}, "time_since_restore": 74227.67835712433, "timesteps_since_restore": 0, "iterations_since_restore": 26}
{"validation_loss": 0.4642425775527954, "validation_mean": 0.5391324162483215, "time_this_iter_s": 2813.7126879692078, "done": false, "timesteps_total": null, "episodes_total": null, "training_iteration": 27, "trial_id": "d56098f2", "experiment_id": "e0994ea7d18644288cf38cad106100d7", "date": "2022-06-14_20-19-24", "timestamp": 1655209164, "time_total_s": 77041.39104509354, "pid": 68460, "hostname": "localhost.localdomain", "node_ip": "192.168.249.74", "config": {"batch_size": 14, "beta1": 0.9, "beta2": 0.999, "lr": 0.0012134882085154237, "weight_decay": 1.3602984953647424e-05, "__trial_index__": 0}, "time_since_restore": 77041.39104509354, "timesteps_since_restore": 0, "iterations_since_restore": 27}
{"validation_loss": 0.5088977813720703, "validation_mean": 0.42781731486320496, "time_this_iter_s": 2815.74018907547, "done": false, "timesteps_total": null, "episodes_total": null, "training_iteration": 28, "trial_id": "d56098f2", "experiment_id": "e0994ea7d18644288cf38cad106100d7", "date": "2022-06-14_21-06-19", "timestamp": 1655211979, "time_total_s": 79857.131234169, "pid": 68460, "hostname": "localhost.localdomain", "node_ip": "192.168.249.74", "config": {"batch_size": 14, "beta1": 0.9, "beta2": 0.999, "lr": 0.0012134882085154237, "weight_decay": 1.3602984953647424e-05, "__trial_index__": 0}, "time_since_restore": 79857.131234169, "timesteps_since_restore": 0, "iterations_since_restore": 28}
{"validation_loss": 0.4620603621006012, "validation_mean": 0.5404330492019653, "time_this_iter_s": 2838.782744884491, "done": false, "timesteps_total": null, "episodes_total": null, "training_iteration": 29, "trial_id": "d56098f2", "experiment_id": "e0994ea7d18644288cf38cad106100d7", "date": "2022-06-14_21-53-38", "timestamp": 1655214818, "time_total_s": 82695.9139790535, "pid": 68460, "hostname": "localhost.localdomain", "node_ip": "192.168.249.74", "config": {"batch_size": 14, "beta1": 0.9, "beta2": 0.999, "lr": 0.0012134882085154237, "weight_decay": 1.3602984953647424e-05, "__trial_index__": 0}, "time_since_restore": 82695.9139790535, "timesteps_since_restore": 0, "iterations_since_restore": 29}
{"validation_loss": 0.52287358045578, "validation_mean": 0.40509524941444397, "time_this_iter_s": 2829.2228412628174, "done": true, "timesteps_total": null, "episodes_total": null, "training_iteration": 30, "trial_id": "d56098f2", "experiment_id": "e0994ea7d18644288cf38cad106100d7", "date": "2022-06-14_22-40-47", "timestamp": 1655217647, "time_total_s": 85525.13682031631, "pid": 68460, "hostname": "localhost.localdomain", "node_ip": "192.168.249.74", "config": {"batch_size": 14, "beta1": 0.9, "beta2": 0.999, "lr": 0.0012134882085154237, "weight_decay": 1.3602984953647424e-05, "__trial_index__": 0}, "time_since_restore": 85525.13682031631, "timesteps_since_restore": 0, "iterations_since_restore": 30}
