{"validation_loss": 0.45978185534477234, "validation_0_f1": 0.6186721920967102, "validation_1_f1": 0.0, "validation_2_f1": 0.7859630584716797, "validation_mean": 0.5666742920875549, "time_this_iter_s": 2535.899599790573, "done": false, "timesteps_total": null, "episodes_total": null, "training_iteration": 1, "trial_id": "0b99bba8", "experiment_id": "ca36e25e0b0845a78fb0e0d0b4bbce3f", "date": "2022-06-30_13-53-44", "timestamp": 1656568424, "time_total_s": 2535.899599790573, "pid": 209740, "hostname": "localhost.localdomain", "node_ip": "192.168.249.74", "config": {"batch_size": 14, "beta1": 0.9, "beta2": 0.999, "lr": 7.3807568977814094e-06, "weight_decay": 0.001474021783211384, "__trial_index__": 0}, "time_since_restore": 2535.899599790573, "timesteps_since_restore": 0, "iterations_since_restore": 1}
{"validation_loss": 0.5127934217453003, "validation_0_f1": 0.5519368648529053, "validation_1_f1": 0.0, "validation_2_f1": 0.412320613861084, "validation_mean": 0.4324076175689697, "time_this_iter_s": 2612.887902021408, "done": true, "timesteps_total": null, "episodes_total": null, "training_iteration": 2, "trial_id": "0b99bba8", "experiment_id": "ca36e25e0b0845a78fb0e0d0b4bbce3f", "date": "2022-06-30_14-37-17", "timestamp": 1656571037, "time_total_s": 5148.787501811981, "pid": 209740, "hostname": "localhost.localdomain", "node_ip": "192.168.249.74", "config": {"batch_size": 14, "beta1": 0.9, "beta2": 0.999, "lr": 7.3807568977814094e-06, "weight_decay": 0.001474021783211384, "__trial_index__": 0}, "time_since_restore": 5148.787501811981, "timesteps_since_restore": 0, "iterations_since_restore": 2}
