{"validation_loss": 0.3440459966659546, "validation_0_f1": 0.8254939913749695, "validation_1_f1": 0.773536205291748, "validation_2_f1": 0.8642839193344116, "validation_mean": 0.8227373361587524, "time_this_iter_s": 2434.6058592796326, "done": false, "timesteps_total": null, "episodes_total": null, "training_iteration": 1, "trial_id": "54e4c31c", "experiment_id": "a43bc2b44b564300a8bcbf3ff3d5240b", "date": "2022-07-01_18-24-51", "timestamp": 1656671091, "time_total_s": 2434.6058592796326, "pid": 110003, "hostname": "localhost.localdomain", "node_ip": "192.168.249.74", "config": {"batch_size": 14, "beta1": 0.9, "beta2": 0.999, "lr": 8.36888581971912e-06, "weight_decay": 0.0009039629025884468, "__trial_index__": 0}, "time_since_restore": 2434.6058592796326, "timesteps_since_restore": 0, "iterations_since_restore": 1}
{"validation_loss": 0.40704309940338135, "validation_0_f1": 0.7092875242233276, "validation_1_f1": 0.6087815761566162, "validation_2_f1": 0.6410612463951111, "validation_mean": 0.6651365756988525, "time_this_iter_s": 2424.642701625824, "done": false, "timesteps_total": null, "episodes_total": null, "training_iteration": 2, "trial_id": "54e4c31c", "experiment_id": "a43bc2b44b564300a8bcbf3ff3d5240b", "date": "2022-07-01_19-05-15", "timestamp": 1656673515, "time_total_s": 4859.2485609054565, "pid": 110003, "hostname": "localhost.localdomain", "node_ip": "192.168.249.74", "config": {"batch_size": 14, "beta1": 0.9, "beta2": 0.999, "lr": 8.36888581971912e-06, "weight_decay": 0.0009039629025884468, "__trial_index__": 0}, "time_since_restore": 4859.2485609054565, "timesteps_since_restore": 0, "iterations_since_restore": 2}
{"validation_loss": 0.36715424060821533, "validation_0_f1": 0.7606210708618164, "validation_1_f1": 0.637365996837616, "validation_2_f1": 0.8692015409469604, "validation_mean": 0.7626042366027832, "time_this_iter_s": 2427.5898838043213, "done": false, "timesteps_total": null, "episodes_total": null, "training_iteration": 3, "trial_id": "54e4c31c", "experiment_id": "a43bc2b44b564300a8bcbf3ff3d5240b", "date": "2022-07-01_19-45-43", "timestamp": 1656675943, "time_total_s": 7286.838444709778, "pid": 110003, "hostname": "localhost.localdomain", "node_ip": "192.168.249.74", "config": {"batch_size": 14, "beta1": 0.9, "beta2": 0.999, "lr": 8.36888581971912e-06, "weight_decay": 0.0009039629025884468, "__trial_index__": 0}, "time_since_restore": 7286.838444709778, "timesteps_since_restore": 0, "iterations_since_restore": 3}
{"validation_loss": 0.3430442214012146, "validation_0_f1": 0.8447323441505432, "validation_1_f1": 0.7843326926231384, "validation_2_f1": 0.8090070486068726, "validation_mean": 0.8155458569526672, "time_this_iter_s": 2426.386395931244, "done": false, "timesteps_total": null, "episodes_total": null, "training_iteration": 4, "trial_id": "54e4c31c", "experiment_id": "a43bc2b44b564300a8bcbf3ff3d5240b", "date": "2022-07-01_20-26-09", "timestamp": 1656678369, "time_total_s": 9713.224840641022, "pid": 110003, "hostname": "localhost.localdomain", "node_ip": "192.168.249.74", "config": {"batch_size": 14, "beta1": 0.9, "beta2": 0.999, "lr": 8.36888581971912e-06, "weight_decay": 0.0009039629025884468, "__trial_index__": 0}, "time_since_restore": 9713.224840641022, "timesteps_since_restore": 0, "iterations_since_restore": 4}
{"validation_loss": 0.36017805337905884, "validation_0_f1": 0.7767364382743835, "validation_1_f1": 0.6515581011772156, "validation_2_f1": 0.8757795095443726, "validation_mean": 0.7749980688095093, "time_this_iter_s": 2414.913963317871, "done": false, "timesteps_total": null, "episodes_total": null, "training_iteration": 5, "trial_id": "54e4c31c", "experiment_id": "a43bc2b44b564300a8bcbf3ff3d5240b", "date": "2022-07-01_21-06-24", "timestamp": 1656680784, "time_total_s": 12128.138803958893, "pid": 110003, "hostname": "localhost.localdomain", "node_ip": "192.168.249.74", "config": {"batch_size": 14, "beta1": 0.9, "beta2": 0.999, "lr": 8.36888581971912e-06, "weight_decay": 0.0009039629025884468, "__trial_index__": 0}, "time_since_restore": 12128.138803958893, "timesteps_since_restore": 0, "iterations_since_restore": 5}
{"validation_loss": 0.3341158330440521, "validation_0_f1": 0.8631495237350464, "validation_1_f1": 0.8121428489685059, "validation_2_f1": 0.8503525853157043, "validation_mean": 0.8430112600326538, "time_this_iter_s": 2421.004048347473, "done": false, "timesteps_total": null, "episodes_total": null, "training_iteration": 6, "trial_id": "54e4c31c", "experiment_id": "a43bc2b44b564300a8bcbf3ff3d5240b", "date": "2022-07-01_21-46-45", "timestamp": 1656683205, "time_total_s": 14549.142852306366, "pid": 110003, "hostname": "localhost.localdomain", "node_ip": "192.168.249.74", "config": {"batch_size": 14, "beta1": 0.9, "beta2": 0.999, "lr": 8.36888581971912e-06, "weight_decay": 0.0009039629025884468, "__trial_index__": 0}, "time_since_restore": 14549.142852306366, "timesteps_since_restore": 0, "iterations_since_restore": 6}
{"validation_loss": 0.3782278895378113, "validation_0_f1": 0.7528677582740784, "validation_1_f1": 0.6718621850013733, "validation_2_f1": 0.7412506937980652, "validation_mean": 0.7271057963371277, "time_this_iter_s": 2419.9300746917725, "done": false, "timesteps_total": null, "episodes_total": null, "training_iteration": 7, "trial_id": "54e4c31c", "experiment_id": "a43bc2b44b564300a8bcbf3ff3d5240b", "date": "2022-07-01_22-27-05", "timestamp": 1656685625, "time_total_s": 16969.07292699814, "pid": 110003, "hostname": "localhost.localdomain", "node_ip": "192.168.249.74", "config": {"batch_size": 14, "beta1": 0.9, "beta2": 0.999, "lr": 8.36888581971912e-06, "weight_decay": 0.0009039629025884468, "__trial_index__": 0}, "time_since_restore": 16969.07292699814, "timesteps_since_restore": 0, "iterations_since_restore": 7}
{"validation_loss": 0.37327975034713745, "validation_0_f1": 0.7856074571609497, "validation_1_f1": 0.6940695643424988, "validation_2_f1": 0.6873693466186523, "validation_mean": 0.7321551442146301, "time_this_iter_s": 2405.842086315155, "done": true, "timesteps_total": null, "episodes_total": null, "training_iteration": 8, "trial_id": "54e4c31c", "experiment_id": "a43bc2b44b564300a8bcbf3ff3d5240b", "date": "2022-07-01_23-07-11", "timestamp": 1656688031, "time_total_s": 19374.915013313293, "pid": 110003, "hostname": "localhost.localdomain", "node_ip": "192.168.249.74", "config": {"batch_size": 14, "beta1": 0.9, "beta2": 0.999, "lr": 8.36888581971912e-06, "weight_decay": 0.0009039629025884468, "__trial_index__": 0}, "time_since_restore": 19374.915013313293, "timesteps_since_restore": 0, "iterations_since_restore": 8}
