{"validation_loss": 0.38731372356414795, "validation_0_f1": 0.0, "validation_1_f1": 0.7597923278808594, "validation_2_f1": 0.6334621906280518, "validation_mean": 0.5659857988357544, "time_this_iter_s": 2876.0713605880737, "done": false, "timesteps_total": null, "episodes_total": null, "training_iteration": 1, "trial_id": "7e21c77a", "experiment_id": "af62f123c4e94b88ae20aeac7c9b315d", "date": "2022-07-01_01-15-42", "timestamp": 1656609342, "time_total_s": 2876.0713605880737, "pid": 209736, "hostname": "localhost.localdomain", "node_ip": "192.168.249.74", "config": {"batch_size": 14, "beta1": 0.9, "beta2": 0.999, "lr": 5.759968630277552e-06, "weight_decay": 0.004177222282951179, "__trial_index__": 0}, "time_since_restore": 2876.0713605880737, "timesteps_since_restore": 0, "iterations_since_restore": 1}
{"validation_loss": 0.4364725649356842, "validation_0_f1": 0.613180935382843, "validation_1_f1": 0.2212171107530594, "validation_2_f1": 0.6600562334060669, "validation_mean": 0.5523678660392761, "time_this_iter_s": 2779.938569545746, "done": false, "timesteps_total": null, "episodes_total": null, "training_iteration": 2, "trial_id": "7e21c77a", "experiment_id": "af62f123c4e94b88ae20aeac7c9b315d", "date": "2022-07-01_02-02-02", "timestamp": 1656612122, "time_total_s": 5656.00993013382, "pid": 209736, "hostname": "localhost.localdomain", "node_ip": "192.168.249.74", "config": {"batch_size": 14, "beta1": 0.9, "beta2": 0.999, "lr": 5.759968630277552e-06, "weight_decay": 0.004177222282951179, "__trial_index__": 0}, "time_since_restore": 5656.00993013382, "timesteps_since_restore": 0, "iterations_since_restore": 2}
{"validation_loss": 0.42041119933128357, "validation_0_f1": 0.6680523753166199, "validation_1_f1": 0.4164222776889801, "validation_2_f1": 0.7847722768783569, "validation_mean": 0.6450921893119812, "time_this_iter_s": 2389.8346633911133, "done": false, "timesteps_total": null, "episodes_total": null, "training_iteration": 3, "trial_id": "7e21c77a", "experiment_id": "af62f123c4e94b88ae20aeac7c9b315d", "date": "2022-07-01_02-41-52", "timestamp": 1656614512, "time_total_s": 8045.844593524933, "pid": 209736, "hostname": "localhost.localdomain", "node_ip": "192.168.249.74", "config": {"batch_size": 14, "beta1": 0.9, "beta2": 0.999, "lr": 5.759968630277552e-06, "weight_decay": 0.004177222282951179, "__trial_index__": 0}, "time_since_restore": 8045.844593524933, "timesteps_since_restore": 0, "iterations_since_restore": 3}
{"validation_loss": 0.3959285020828247, "validation_0_f1": 0.7568673491477966, "validation_1_f1": 0.7074570059776306, "validation_2_f1": 0.8172615766525269, "validation_mean": 0.7583964467048645, "time_this_iter_s": 2386.682146549225, "done": true, "timesteps_total": null, "episodes_total": null, "training_iteration": 4, "trial_id": "7e21c77a", "experiment_id": "af62f123c4e94b88ae20aeac7c9b315d", "date": "2022-07-01_03-21-39", "timestamp": 1656616899, "time_total_s": 10432.526740074158, "pid": 209736, "hostname": "localhost.localdomain", "node_ip": "192.168.249.74", "config": {"batch_size": 14, "beta1": 0.9, "beta2": 0.999, "lr": 5.759968630277552e-06, "weight_decay": 0.004177222282951179, "__trial_index__": 0}, "time_since_restore": 10432.526740074158, "timesteps_since_restore": 0, "iterations_since_restore": 4}
