{"validation_loss": 0.3760160803794861, "validation_0_f1": 0.0013286094181239605, "validation_1_f1": 0.5926035046577454, "validation_2_f1": 0.8596621751785278, "validation_mean": 0.5727182030677795, "time_this_iter_s": 2873.0487246513367, "done": false, "timesteps_total": null, "episodes_total": null, "training_iteration": 1, "trial_id": "46ac0422", "experiment_id": "d899d1d1862a4382b96c4fc35909863e", "date": "2022-06-27_20-17-50", "timestamp": 1656332270, "time_total_s": 2873.0487246513367, "pid": 156472, "hostname": "localhost.localdomain", "node_ip": "192.168.249.74", "config": {"batch_size": 14, "beta1": 0.9, "beta2": 0.999, "lr": 8.554473915303258e-06, "weight_decay": 0.0022853344530036446, "__trial_index__": 0}, "time_since_restore": 2873.0487246513367, "timesteps_since_restore": 0, "iterations_since_restore": 1}
{"validation_loss": 0.4233689308166504, "validation_0_f1": 0.6620157361030579, "validation_1_f1": 0.4815566837787628, "validation_2_f1": 0.6726842522621155, "validation_mean": 0.6239767670631409, "time_this_iter_s": 2951.8655858039856, "done": false, "timesteps_total": null, "episodes_total": null, "training_iteration": 2, "trial_id": "46ac0422", "experiment_id": "d899d1d1862a4382b96c4fc35909863e", "date": "2022-06-27_21-07-02", "timestamp": 1656335222, "time_total_s": 5824.914310455322, "pid": 156472, "hostname": "localhost.localdomain", "node_ip": "192.168.249.74", "config": {"batch_size": 14, "beta1": 0.9, "beta2": 0.999, "lr": 8.554473915303258e-06, "weight_decay": 0.0022853344530036446, "__trial_index__": 0}, "time_since_restore": 5824.914310455322, "timesteps_since_restore": 0, "iterations_since_restore": 2}
{"validation_loss": 0.40068507194519043, "validation_0_f1": 0.7443728446960449, "validation_1_f1": 0.772311806678772, "validation_2_f1": 0.6905643343925476, "validation_mean": 0.7384285926818848, "time_this_iter_s": 3105.212414741516, "done": false, "timesteps_total": null, "episodes_total": null, "training_iteration": 3, "trial_id": "46ac0422", "experiment_id": "d899d1d1862a4382b96c4fc35909863e", "date": "2022-06-27_21-58-47", "timestamp": 1656338327, "time_total_s": 8930.126725196838, "pid": 156472, "hostname": "localhost.localdomain", "node_ip": "192.168.249.74", "config": {"batch_size": 14, "beta1": 0.9, "beta2": 0.999, "lr": 8.554473915303258e-06, "weight_decay": 0.0022853344530036446, "__trial_index__": 0}, "time_since_restore": 8930.126725196838, "timesteps_since_restore": 0, "iterations_since_restore": 3}
{"validation_loss": 0.3761026859283447, "validation_0_f1": 0.8456230163574219, "validation_1_f1": 0.8300114274024963, "validation_2_f1": 0.782608687877655, "validation_mean": 0.8228903412818909, "time_this_iter_s": 3353.3023879528046, "done": false, "timesteps_total": null, "episodes_total": null, "training_iteration": 4, "trial_id": "46ac0422", "experiment_id": "d899d1d1862a4382b96c4fc35909863e", "date": "2022-06-27_22-54-40", "timestamp": 1656341680, "time_total_s": 12283.429113149643, "pid": 156472, "hostname": "localhost.localdomain", "node_ip": "192.168.249.74", "config": {"batch_size": 14, "beta1": 0.9, "beta2": 0.999, "lr": 8.554473915303258e-06, "weight_decay": 0.0022853344530036446, "__trial_index__": 0}, "time_since_restore": 12283.429113149643, "timesteps_since_restore": 0, "iterations_since_restore": 4}
{"validation_loss": 0.416088730096817, "validation_0_f1": 0.6653711199760437, "validation_1_f1": 0.6610915660858154, "validation_2_f1": 0.5172355771064758, "validation_mean": 0.6305561661720276, "time_this_iter_s": 3405.4186294078827, "done": false, "timesteps_total": null, "episodes_total": null, "training_iteration": 5, "trial_id": "46ac0422", "experiment_id": "d899d1d1862a4382b96c4fc35909863e", "date": "2022-06-27_23-51-26", "timestamp": 1656345086, "time_total_s": 15688.847742557526, "pid": 156472, "hostname": "localhost.localdomain", "node_ip": "192.168.249.74", "config": {"batch_size": 14, "beta1": 0.9, "beta2": 0.999, "lr": 8.554473915303258e-06, "weight_decay": 0.0022853344530036446, "__trial_index__": 0}, "time_since_restore": 15688.847742557526, "timesteps_since_restore": 0, "iterations_since_restore": 5}
{"validation_loss": 0.35810062289237976, "validation_0_f1": 0.795135498046875, "validation_1_f1": 0.8386861085891724, "validation_2_f1": 0.6983231902122498, "validation_mean": 0.7838727235794067, "time_this_iter_s": 3166.7112407684326, "done": false, "timesteps_total": null, "episodes_total": null, "training_iteration": 6, "trial_id": "46ac0422", "experiment_id": "d899d1d1862a4382b96c4fc35909863e", "date": "2022-06-28_00-44-13", "timestamp": 1656348253, "time_total_s": 18855.55898332596, "pid": 156472, "hostname": "localhost.localdomain", "node_ip": "192.168.249.74", "config": {"batch_size": 14, "beta1": 0.9, "beta2": 0.999, "lr": 8.554473915303258e-06, "weight_decay": 0.0022853344530036446, "__trial_index__": 0}, "time_since_restore": 18855.55898332596, "timesteps_since_restore": 0, "iterations_since_restore": 6}
{"validation_loss": 0.36865100264549255, "validation_0_f1": 0.7690848112106323, "validation_1_f1": 0.8120015263557434, "validation_2_f1": 0.6718797087669373, "validation_mean": 0.7573253512382507, "time_this_iter_s": 2878.208249807358, "done": false, "timesteps_total": null, "episodes_total": null, "training_iteration": 7, "trial_id": "46ac0422", "experiment_id": "d899d1d1862a4382b96c4fc35909863e", "date": "2022-06-28_01-32-11", "timestamp": 1656351131, "time_total_s": 21733.767233133316, "pid": 156472, "hostname": "localhost.localdomain", "node_ip": "192.168.249.74", "config": {"batch_size": 14, "beta1": 0.9, "beta2": 0.999, "lr": 8.554473915303258e-06, "weight_decay": 0.0022853344530036446, "__trial_index__": 0}, "time_since_restore": 21733.767233133316, "timesteps_since_restore": 0, "iterations_since_restore": 7}
{"validation_loss": 0.3816235363483429, "validation_0_f1": 0.72752445936203, "validation_1_f1": 0.732867956161499, "validation_2_f1": 0.7064152956008911, "validation_mean": 0.7234335541725159, "time_this_iter_s": 2843.7450847625732, "done": false, "timesteps_total": null, "episodes_total": null, "training_iteration": 8, "trial_id": "46ac0422", "experiment_id": "d899d1d1862a4382b96c4fc35909863e", "date": "2022-06-28_02-19-35", "timestamp": 1656353975, "time_total_s": 24577.51231789589, "pid": 156472, "hostname": "localhost.localdomain", "node_ip": "192.168.249.74", "config": {"batch_size": 14, "beta1": 0.9, "beta2": 0.999, "lr": 8.554473915303258e-06, "weight_decay": 0.0022853344530036446, "__trial_index__": 0}, "time_since_restore": 24577.51231789589, "timesteps_since_restore": 0, "iterations_since_restore": 8}
{"validation_loss": 0.34711360931396484, "validation_0_f1": 0.8368327021598816, "validation_1_f1": 0.8145584464073181, "validation_2_f1": 0.7679596543312073, "validation_mean": 0.8108790516853333, "time_this_iter_s": 2836.07510972023, "done": false, "timesteps_total": null, "episodes_total": null, "training_iteration": 9, "trial_id": "46ac0422", "experiment_id": "d899d1d1862a4382b96c4fc35909863e", "date": "2022-06-28_03-06-51", "timestamp": 1656356811, "time_total_s": 27413.58742761612, "pid": 156472, "hostname": "localhost.localdomain", "node_ip": "192.168.249.74", "config": {"batch_size": 14, "beta1": 0.9, "beta2": 0.999, "lr": 8.554473915303258e-06, "weight_decay": 0.0022853344530036446, "__trial_index__": 0}, "time_since_restore": 27413.58742761612, "timesteps_since_restore": 0, "iterations_since_restore": 9}
{"validation_loss": 0.3705878257751465, "validation_0_f1": 0.7588905692100525, "validation_1_f1": 0.7741076350212097, "validation_2_f1": 0.7180232405662537, "validation_mean": 0.7525055408477783, "time_this_iter_s": 2831.5296127796173, "done": false, "timesteps_total": null, "episodes_total": null, "training_iteration": 10, "trial_id": "46ac0422", "experiment_id": "d899d1d1862a4382b96c4fc35909863e", "date": "2022-06-28_03-54-02", "timestamp": 1656359642, "time_total_s": 30245.117040395737, "pid": 156472, "hostname": "localhost.localdomain", "node_ip": "192.168.249.74", "config": {"batch_size": 14, "beta1": 0.9, "beta2": 0.999, "lr": 8.554473915303258e-06, "weight_decay": 0.0022853344530036446, "__trial_index__": 0}, "time_since_restore": 30245.117040395737, "timesteps_since_restore": 0, "iterations_since_restore": 10}
{"validation_loss": 0.3510398268699646, "validation_0_f1": 0.8188976645469666, "validation_1_f1": 0.8327999114990234, "validation_2_f1": 0.729085385799408, "validation_mean": 0.7999387979507446, "time_this_iter_s": 2807.8803992271423, "done": false, "timesteps_total": null, "episodes_total": null, "training_iteration": 11, "trial_id": "46ac0422", "experiment_id": "d899d1d1862a4382b96c4fc35909863e", "date": "2022-06-28_04-40-50", "timestamp": 1656362450, "time_total_s": 33052.99743962288, "pid": 156472, "hostname": "localhost.localdomain", "node_ip": "192.168.249.74", "config": {"batch_size": 14, "beta1": 0.9, "beta2": 0.999, "lr": 8.554473915303258e-06, "weight_decay": 0.0022853344530036446, "__trial_index__": 0}, "time_since_restore": 33052.99743962288, "timesteps_since_restore": 0, "iterations_since_restore": 11}
{"validation_loss": 0.3762449622154236, "validation_0_f1": 0.7433145642280579, "validation_1_f1": 0.7860733270645142, "validation_2_f1": 0.6713011860847473, "validation_mean": 0.7384285926818848, "time_this_iter_s": 2831.910059928894, "done": false, "timesteps_total": null, "episodes_total": null, "training_iteration": 12, "trial_id": "46ac0422", "experiment_id": "d899d1d1862a4382b96c4fc35909863e", "date": "2022-06-28_05-28-02", "timestamp": 1656365282, "time_total_s": 35884.90749955177, "pid": 156472, "hostname": "localhost.localdomain", "node_ip": "192.168.249.74", "config": {"batch_size": 14, "beta1": 0.9, "beta2": 0.999, "lr": 8.554473915303258e-06, "weight_decay": 0.0022853344530036446, "__trial_index__": 0}, "time_since_restore": 35884.90749955177, "timesteps_since_restore": 0, "iterations_since_restore": 12}
{"validation_loss": 0.39142587780952454, "validation_0_f1": 0.7559322118759155, "validation_1_f1": 0.7526881694793701, "validation_2_f1": 0.5096104741096497, "validation_mean": 0.6994873881340027, "time_this_iter_s": 2830.1584272384644, "done": false, "timesteps_total": null, "episodes_total": null, "training_iteration": 13, "trial_id": "46ac0422", "experiment_id": "d899d1d1862a4382b96c4fc35909863e", "date": "2022-06-28_06-15-12", "timestamp": 1656368112, "time_total_s": 38715.06592679024, "pid": 156472, "hostname": "localhost.localdomain", "node_ip": "192.168.249.74", "config": {"batch_size": 14, "beta1": 0.9, "beta2": 0.999, "lr": 8.554473915303258e-06, "weight_decay": 0.0022853344530036446, "__trial_index__": 0}, "time_since_restore": 38715.06592679024, "timesteps_since_restore": 0, "iterations_since_restore": 13}
{"validation_loss": 0.365617036819458, "validation_0_f1": 0.774078369140625, "validation_1_f1": 0.7467833161354065, "validation_2_f1": 0.7668480277061462, "validation_mean": 0.7639813423156738, "time_this_iter_s": 2832.077059984207, "done": false, "timesteps_total": null, "episodes_total": null, "training_iteration": 14, "trial_id": "46ac0422", "experiment_id": "d899d1d1862a4382b96c4fc35909863e", "date": "2022-06-28_07-02-24", "timestamp": 1656370944, "time_total_s": 41547.142986774445, "pid": 156472, "hostname": "localhost.localdomain", "node_ip": "192.168.249.74", "config": {"batch_size": 14, "beta1": 0.9, "beta2": 0.999, "lr": 8.554473915303258e-06, "weight_decay": 0.0022853344530036446, "__trial_index__": 0}, "time_since_restore": 41547.142986774445, "timesteps_since_restore": 0, "iterations_since_restore": 14}
{"validation_loss": 0.3714306950569153, "validation_0_f1": 0.7567245364189148, "validation_1_f1": 0.7870882749557495, "validation_2_f1": 0.6984127163887024, "validation_mean": 0.7503634095191956, "time_this_iter_s": 2853.5403134822845, "done": false, "timesteps_total": null, "episodes_total": null, "training_iteration": 15, "trial_id": "46ac0422", "experiment_id": "d899d1d1862a4382b96c4fc35909863e", "date": "2022-06-28_07-49-58", "timestamp": 1656373798, "time_total_s": 44400.68330025673, "pid": 156472, "hostname": "localhost.localdomain", "node_ip": "192.168.249.74", "config": {"batch_size": 14, "beta1": 0.9, "beta2": 0.999, "lr": 8.554473915303258e-06, "weight_decay": 0.0022853344530036446, "__trial_index__": 0}, "time_since_restore": 44400.68330025673, "timesteps_since_restore": 0, "iterations_since_restore": 15}
